tateishi_readability.py
tateishi_readability-0.1.0.dist-info/METADATA
tateishi_readability-0.1.0.dist-info/WHEEL
tateishi_readability-0.1.0.dist-info/top_level.txt
tateishi_readability-0.1.0.dist-info/RECORD
