Metadata-Version: 2.1
Name: tateishi-readability
Version: 0.1.0
Summary: Calculate Readability for Japanese Document using Tateishi Index
Home-page: https://github.com/ShinyaAkagiI/tateishi_readability
Author: Shinya Akagi
License: PSF
Platform: UNKNOWN
Requires-Dist: divide-char-type
